multiversion_backup/__init__.py
multiversion_backup/backup.py
multiversion_backup/directory_creator.py
multiversion_backup/log.py
multiversion_backup/path_constants.py
multiversion_backup-1.0.2.dist-info/METADATA
multiversion_backup-1.0.2.dist-info/WHEEL
multiversion_backup-1.0.2.dist-info/RECORD
