Metadata-Version: 2.1
Name: multiversion-backup
Version: 1.0.2
Summary: A 'BackUp' class which copies a target file or folder to set output folders. Detects and keeps a set amount of backup versions and deletes old backups outside that range.
License: MIT
Author: Kyle Ross
Author-email: 107285758+Kyle-Ross@users.noreply.github.com
Requires-Python: >=3.12,<4.0
Classifier: License :: OSI Approved :: MIT License
Classifier: Programming Language :: Python :: 3
Classifier: Programming Language :: Python :: 3.12
